booty/__init__.py
booty/app.py
booty/ast_util.py
booty/cli.py
booty/execute.py
booty/graph.py
booty/lang/__init__.py
booty/lang/grammar.lark
booty/lang/stdlib.booty
booty/parser.py
booty/target_logger.py
booty/types.py
booty/ui.py
booty/validation.py
booty_cli-1.0.14.dist-info/METADATA
booty_cli-1.0.14.dist-info/WHEEL
booty_cli-1.0.14.dist-info/entry_points.txt
booty_cli-1.0.14.dist-info/RECORD
