Metadata-Version: 2.1
Name: booty-cli
Version: 1.0.14
Summary: A language and command line utility for bootstrapping the setup of personal OS installs.
Home-page: https://github.com/naddeoa/booty
License: MIT
Keywords: bootstrap,booty,setup,cli,tool
Author: Anthony Naddeo
Author-email: anthony.naddeo@gmail.com
Requires-Python: >=3.9,<3.13
Classifier: License :: OSI Approved :: MIT License
Classifier: Programming Language :: Python :: 3
Classifier: Programming Language :: Python :: 3.9
Classifier: Programming Language :: Python :: 3.10
Classifier: Programming Language :: Python :: 3.11
Classifier: Programming Language :: Python :: 3.12
Requires-Dist: click (>=8.1.7,<9.0.0)
Requires-Dist: lark (>=1.1.8,<2.0.0)
Requires-Dist: rich (>=13.7.0,<14.0.0)
Project-URL: Repository, https://github.com/naddeoa/booty
